tilelink/__init__.py
tilelink/tsi.py
tilelink-2023.12.28.dist-info/LICENSE
tilelink-2023.12.28.dist-info/METADATA
tilelink-2023.12.28.dist-info/WHEEL
tilelink-2023.12.28.dist-info/top_level.txt
tilelink-2023.12.28.dist-info/RECORD
